{
  "resourceType": "ValueSet",
  "id": "v3-IntegrityCheckAlgorithm",
  "meta": {
    "lastUpdated": "2014-12-11T00:00:00.000+00:00"
  },
  "text": {
    "status": "generated",
    "div": "<div><p>Release Date: 2014-12-11</p>\r\n<p>OID for code system: 2.16.840.1.113883.5.1010</p>\r\n<p>OID for value set: 2.16.840.1.113883.1.11.17385 (this is the value set that includes the entire code system)</p>\r\n<table class=\"grid\">\r\n <tr><td><b>Level</b></td><td><b>Code</b></td><td><b>Display</b></td><td><b>Definition</b></td></tr>\r\n <tr><td>1</td><td>SHA-1<a name=\"SHA-1\"> </a></td><td>secure hash algorithm - 1</td><td>\n                        This algorithm is defined in FIPS PUB 180-1: Secure Hash Standard.  As of April 17, 1995.<br/>\r\n\n                     </td></tr>\r\n <tr><td>1</td><td>SHA-256<a name=\"SHA-256\"> </a></td><td>secure hash algorithm - 256</td><td>\n                        This algorithm is defined in FIPS PUB 180-2: Secure Hash Standard.<br/>\r\n\n                     </td></tr>\r\n</table>\r\n</div>"
  },
  "http://hl7.org/fhir/ExtensionDefinition/valueset-oid": [
    {
      "valueUri": "urn:oid:2.16.840.1.113883.1.11.17385"
    }
  ],
  "identifier": "http://hl7.org/fhir/v3/vs/IntegrityCheckAlgorithm",
  "name": "v3 Code System IntegrityCheckAlgorithm",
  "publisher": "HL7, Inc",
  "telecom": [
    {
      "system": "url",
      "value": "http://hl7.org"
    }
  ],
  "description": "? not found",
  "status": "active",
  "date": "2014-12-11",
  "define": {
    "http://hl7.org/fhir/ExtensionDefinition/valueset-oid": [
      {
        "valueUri": "urn:oid:2.16.840.1.113883.5.1010"
      }
    ],
    "system": "http://hl7.org/fhir/v3/IntegrityCheckAlgorithm",
    "caseSensitive": true,
    "concept": [
      {
        "code": "SHA-1",
        "display": "secure hash algorithm - 1",
        "definition": "This algorithm is defined in FIPS PUB 180-1: Secure Hash Standard.  As of April 17, 1995."
      },
      {
        "code": "SHA-256",
        "display": "secure hash algorithm - 256",
        "definition": "This algorithm is defined in FIPS PUB 180-2: Secure Hash Standard."
      }
    ]
  }
}